Computer-architecture/cache.v
module cache_l1 (
    input clk,
    input rst_n,
    input [31:0] addr,      // Địa chỉ từ CPU
    input [31:0] ram_data,  // Dữ liệu từ RAM (để nạp vào Cache)
    output reg [31:0] cpu_data, // Dữ liệu trả về CPU
    output reg hit,         // Báo Hit cho CPU
    output reg stall,       // Báo Stall (dừng) cho CPU
    output reg ram_read     // Lệnh đọc RAM
);

    // Cấu trúc Cache: 64 dòng (Lines)
    reg [31:0] data_mem [0:63];
    reg [23:0] tag_mem  [0:63];
    reg        valid_mem[0:63];

    // Tách địa chỉ: Tag (24 bit) - Index (6 bit) - Offset (2 bit)
    wire [5:0] index = addr[7:2];
    wire [23:0] tag  = addr[31:8];

    // Máy trạng thái (FSM)
    parameter IDLE = 0, ALLOCATE = 1;
    reg state;

    always @(posedge clk or negedge rst_n) begin
        if (!rst_n) begin
            state <= IDLE;
            hit <= 0; stall <= 0; ram_read <= 0;
            // Reset toàn bộ Valid bit (lặp thủ công hoặc dùng loop trong testbench)
             valid_mem[index] <= 0; 
        end else begin
            case (state)
                IDLE: begin
                    // Kiểm tra: Valid = 1 VÀ Tag khớp
                    if (valid_mem[index] && (tag_mem[index] == tag)) begin
                        // --- CACHE HIT ---
                        hit <= 1;
                        stall <= 0;
                        cpu_data <= data_mem[index];
                        ram_read <= 0;
                    end else begin
                        // --- CACHE MISS ---
                        hit <= 0;
                        stall <= 1; // Yêu cầu CPU dừng
                        ram_read <= 1; // Yêu cầu đọc RAM
                        state <= ALLOCATE; // Chuyển trạng thái
                    end
                end

                ALLOCATE: begin
                    // --- REFILL CACHE ---
                    // Giả lập RAM đã trả dữ liệu về (ram_data)
                    data_mem[index] <= ram_data; // Ghi dữ liệu vào Cache
                    tag_mem[index]  <= tag;      // Cập nhật Tag
                    valid_mem[index]<= 1;        // Đánh dấu Valid
                    
                    stall <= 0; // Hết Stall
                    state <= IDLE; // Quay về kiểm tra lại
                end
            endcase
        end
    end
endmodule

Computer-architecture/ram.v
module data_ram (
    input clk,
    input [31:0] addr,
    input we, // Write Enable
    input [31:0] data_in,
    output reg [31:0] data_out
);
    reg [31:0] memory [0:1023]; // RAM 1KB

    always @(posedge clk) begin
        if (we) begin
            memory[addr[9:2]] <= data_in; // Ghi
        end
        // Đọc RAM luôn luôn trả về dữ liệu mẫu để test Cache Miss
        // Giả sử tại địa chỉ 0x80000010 có dữ liệu AABBCCDD
        if (addr == 32'h80000010)
            data_out <= 32'hAABBCCDD;
        else
            data_out <= memory[addr[9:2]];
    end
endmodule

Computer-architecture/rom.v
module instruction_rom (
    input [31:0] addr,
    output reg [31:0] data_out
);
    always @(*) begin
        // Giả lập nội dung ROM: Nếu đọc địa chỉ 4 thì trả về DEADBEEF
        if (addr == 32'h00000004)
            data_out = 32'hDEADBEEF; // Mã lệnh mẫu
        else
            data_out = 32'h00000000;
    end
endmodule

Computer-architecture/tlb.v
module tlb (
    input [31:0] virt_addr,
    output [31:0] phys_addr,
    output hit
);
    // Trong demo này, TLB ánh xạ 1:1 (Direct Map) để đơn giản
    assign phys_addr = virt_addr; 
    assign hit = 1'b1; // Luôn luôn Hit
endmodule

Computer-architecture/system_top.v
`include "rom.v"
`include "ram.v"
`include "cache.v"
`include "tlb.v"

module system_top (
    input clk,
    input rst_n,
    input [31:0] cpu_virt_addr, // CPU chỉ đưa ra địa chỉ ảo
    output [31:0] cpu_data_in,
    output stall_cpu,
    output cache_hit
);

    // Dây nối nội bộ
    wire [31:0] phys_addr;
    wire tlb_hit;
    
    wire [31:0] rom_out, ram_out, cache_out;
    wire ram_read_req;
    
    // 1. TLB: Dịch địa chỉ
    tlb u_tlb (
        .virt_addr(cpu_virt_addr), 
        .phys_addr(phys_addr), 
        .hit(tlb_hit)
    );

    // 2. Address Decoder (Logic chọn ROM hay RAM)
    reg [31:0] memory_bus_data;
    // Nếu bit cao nhất là 0 -> ROM. Nếu là 1 -> RAM
    wire is_rom = (phys_addr[31] == 1'b0);
    
    // 3. ROM
    instruction_rom u_rom (.addr(phys_addr), .data_out(rom_out));

    // 4. RAM
    data_ram u_ram (
        .clk(clk), .addr(phys_addr), .we(1'b0), 
        .data_in(32'b0), .data_out(ram_out)
    );

    // Logic Mux chọn dữ liệu nạp vào Cache
    always @(*) begin
        if (is_rom) memory_bus_data = rom_out;
        else        memory_bus_data = ram_out;
    end

    // 5. Cache L1
    cache_l1 u_cache (
        .clk(clk), .rst_n(rst_n),
        .addr(phys_addr),
        .ram_data(memory_bus_data), // Nối vào bus chung
        .cpu_data(cpu_data_in),
        .hit(cache_hit),
        .stall(stall_cpu),
        .ram_read(ram_read_req)
    );

endmodule

Computer-architecture/tb_system.v
`timescale 1ns/1ps

module tb_system;
    reg clk;
    reg rst_n;
    reg [31:0] cpu_addr;
    wire [31:0] data_returned;
    wire stall, hit;

    // Gọi module toàn hệ thống ra test
    system_top ut (
        .clk(clk),
        .rst_n(rst_n),
        .cpu_virt_addr(cpu_addr),
        .cpu_data_in(data_returned),
        .stall_cpu(stall),
        .cache_hit(hit)
    );

    // Tạo xung nhịp (Clock)
    always #5 clk = ~clk; // Chu kỳ 10ns

    initial begin
        // Thiết lập file để xem sóng trên GTKWave
        $dumpfile("waveform.vcd");
        $dumpvars(0, tb_system);

        // --- KHỞI TẠO ---
        clk = 0; rst_n = 0; cpu_addr = 0;
        #10 rst_n = 1; // Thả Reset

        // ==========================================
        // KỊCH BẢN 1: Đọc ROM (Địa chỉ thấp)
        // ==========================================
        #20;
        $display("Time %t: [TEST 1] Accessing ROM at 0x00000004", $time);
        cpu_addr = 32'h00000004; 
        // Kỳ vọng: Dữ liệu DEADBEEF trả về. (Cache có thể Miss nhưng vẫn có dữ liệu)
        
        #30; // Chờ một chút

        // ==========================================
        // KỊCH BẢN 2: Đọc RAM (Cache Miss & Refill)
        // ==========================================
        $display("Time %t: [TEST 2] Accessing RAM at 0x80000010 (First Time - MISS)", $time);
        cpu_addr = 32'h80000010; 
        
        // Logic mô phỏng:
        // 1. Cache check -> Miss (hit=0)
        // 2. Stall -> lên 1
        // 3. Đọc RAM -> trả về AABBCCDD
        // 4. Stall -> xuống 0
        
        wait(stall == 0); // Chờ cho đến khi hết Stall (Refill xong)
        #10;

        // ==========================================
        // KỊCH BẢN 3: Đọc RAM (Cache Hit)
        // ==========================================
        $display("Time %t: [TEST 3] Accessing RAM at 0x80000010 (Second Time - HIT)", $time);
        // Giữ nguyên địa chỉ cũ, chỉ cần quan sát tín hiệu
        #10;
        
        // Kết thúc mô phỏng
        #50 $finish;
    end
endmodule

Computer-architecture/waveform.vcd
$date
	Mon Dec 29 01:34:42 2025
$end
$version
	Icarus Verilog
$end
$timescale
	1ps
$end
$scope module tb_system $end
$var wire 1 ! stall $end
$var wire 1 " hit $end
$var wire 32 # data_returned [31:0] $end
$var reg 1 $ clk $end
$var reg 32 % cpu_addr [31:0] $end
$var reg 1 & rst_n $end
$scope module ut $end
$var wire 1 $ clk $end
$var wire 32 ' cpu_virt_addr [31:0] $end
$var wire 1 ( is_rom $end
$var wire 1 & rst_n $end
$var wire 1 ) tlb_hit $end
$var wire 1 ! stall_cpu $end
$var wire 32 * rom_out [31:0] $end
$var wire 1 + ram_read_req $end
$var wire 32 , ram_out [31:0] $end
$var wire 32 - phys_addr [31:0] $end
$var wire 32 . cpu_data_in [31:0] $end
$var wire 1 " cache_hit $end
$var reg 32 / memory_bus_data [31:0] $end
$scope module u_cache $end
$var wire 1 $ clk $end
$var wire 32 0 ram_data [31:0] $end
$var wire 1 & rst_n $end
$var wire 24 1 tag [23:0] $end
$var wire 6 2 index [5:0] $end
$var wire 32 3 addr [31:0] $end
$var parameter 32 4 ALLOCATE $end
$var parameter 32 5 IDLE $end
$var reg 32 6 cpu_data [31:0] $end
$var reg 1 " hit $end
$var reg 1 + ram_read $end
$var reg 1 ! stall $end
$var reg 1 7 state $end
$upscope $end
$scope module u_ram $end
$var wire 1 $ clk $end
$var wire 32 8 data_in [31:0] $end
$var wire 1 9 we $end
$var wire 32 : addr [31:0] $end
$var reg 32 ; data_out [31:0] $end
$upscope $end
$scope module u_rom $end
$var wire 32 < addr [31:0] $end
$var reg 32 = data_out [31:0] $end
$upscope $end
$scope module u_tlb $end
$var wire 1 ) hit $end
$var wire 32 > phys_addr [31:0] $end
$var wire 32 ? virt_addr [31:0] $end
$upscope $end
$upscope $end
$upscope $end
$enddefinitions $end
$comment Show the parameter values. $end
$dumpall
b0 5
b1 4
$end
#0
$dumpvars
b0 ?
b0 >
b0 =
b0 <
bx ;
b0 :
09
b0 8
07
bx 6
b0 3
b0 2
b0 1
b0 0
b0 /
bx .
b0 -
bx ,
0+
b0 *
1)
1(
b0 '
0&
b0 %
0$
bx #
0"
0!
$end
#5000
1$
#10000
0$
1&
#15000
17
1+
1!
1$
#20000
0$
#25000
07
0!
1$
#30000
b11011110101011011011111011101111 /
b11011110101011011011111011101111 0
b1 2
b11011110101011011011111011101111 *
b11011110101011011011111011101111 =
0$
b100 -
b100 3
b100 :
b100 <
b100 >
b100 %
b100 '
b100 ?
#35000
17
1!
1$
#40000
0$
#45000
07
0!
1$
#50000
0$
#55000
0+
b11011110101011011011111011101111 #
b11011110101011011011111011101111 .
b11011110101011011011111011101111 6
1"
1$
#60000
0(
bx /
bx 0
b100000000000000000000000 1
b100 2
b0 *
b0 =
0$
b10000000000000000000000000010000 -
b10000000000000000000000000010000 3
b10000000000000000000000000010000 :
b10000000000000000000000000010000 <
b10000000000000000000000000010000 >
b10000000000000000000000000010000 %
b10000000000000000000000000010000 '
b10000000000000000000000000010000 ?
#65000
b10101010101110111100110011011101 /
b10101010101110111100110011011101 0
17
1+
1!
0"
b10101010101110111100110011011101 ,
b10101010101110111100110011011101 ;
1$
#70000
0$
#75000
07
0!
1$
#80000
0$
#85000
0+
b10101010101110111100110011011101 #
b10101010101110111100110011011101 .
b10101010101110111100110011011101 6
1"
1$
